mkie/__init__.py
mkie/__main__.py
mkie/core/__init__.py
mkie/core/mkdk.py
mkie/core/mkgit.py
mkie/core/toolkit.py
mkie-0.1.10.dist-info/LICENSE
mkie-0.1.10.dist-info/METADATA
mkie-0.1.10.dist-info/WHEEL
mkie-0.1.10.dist-info/entry_points.txt
mkie-0.1.10.dist-info/RECORD
